easyPlog/__init__.py
easyPlog/easyPlog.py
easyPlog-1.1.dist-info/LICENSE
easyPlog-1.1.dist-info/METADATA
easyPlog-1.1.dist-info/WHEEL
easyPlog-1.1.dist-info/top_level.txt
easyPlog-1.1.dist-info/RECORD
