Metadata-Version: 2.1
Name: easyPlog
Version: 1.1
Summary: This is a easy way to use log.
Home-page: UNKNOWN
Author: yangqiang
Author-email: whuhit09@gmail.com
License: UNKNOWN
Platform: UNKNOWN
